{
  "main": {
    "id": "80f7c2a57a67ba75",
    "type": "split",
    "children": [
      {
        "id": "386daaf12777122c",
        "type": "tabs",
        "children": [
          {
            "id": "b18c23c7b47d33fe",
            "type": "leaf",
            "state": {
              "type": "markdown",
              "state": {
                "file": "services.md",
                "mode": "source",
                "source": false
              },
              "icon": "lucide-file",
              "title": "services"
            }
          },
          {
            "id": "efce14b5c734110f",
            "type": "leaf",
            "state": {
              "type": "markdown",
              "state": {
                "file": "list of lines.md",
                "mode": "source",
                "source": false
              },
              "icon": "lucide-file",
              "title": "list of lines"
            }
          }
        ],
        "currentTab": 1
      }
    ],
    "direction": "vertical"
  },
  "left": {
    "id": "58f9e5e6c5049f9a",
    "type": "split",
    "children": [
      {
        "id": "7b0813035c6f1ac6",
        "type": "tabs",
        "children": [
          {
            "id": "be623665b7be801e",
            "type": "leaf",
            "state": {
              "type": "file-explorer",
              "state": {
                "sortOrder": "alphabetical",
                "autoReveal": false
              },
              "icon": "lucide-folder-closed",
              "title": "Files"
            }
          },
          {
            "id": "12b817fa3ea3c72f",
            "type": "leaf",
            "state": {
              "type": "search",
              "state": {
                "query": "",
                "matchingCase": false,
                "explainSearch": false,
                "collapseAll": false,
                "extraContext": false,
                "sortOrder": "alphabetical"
              },
              "icon": "lucide-search",
              "title": "Search"
            }
          },
          {
            "id": "854a56dcabdfa673",
            "type": "leaf",
            "state": {
              "type": "bookmarks",
              "state": {},
              "icon": "lucide-bookmark",
              "title": "Bookmarks"
            }
          }
        ],
        "currentTab": 1
      }
    ],
    "direction": "horizontal",
    "width": 300,
    "collapsed": true
  },
  "right": {
    "id": "720aea09317ee5be",
    "type": "split",
    "children": [
      {
        "id": "b1c07c764aa7b0a7",
        "type": "tabs",
        "children": [
          {
            "id": "06cdad9b9d3c6c69",
            "type": "leaf",
            "state": {
              "type": "backlink",
              "state": {
                "file": "design.md",
                "collapseAll": false,
                "extraContext": false,
                "sortOrder": "alphabetical",
                "showSearch": false,
                "searchQuery": "",
                "backlinkCollapsed": false,
                "unlinkedCollapsed": true
              },
              "icon": "links-coming-in",
              "title": "Backlinks for design"
            }
          },
          {
            "id": "84376fdd88c36408",
            "type": "leaf",
            "state": {
              "type": "outgoing-link",
              "state": {
                "file": "design.md",
                "linksCollapsed": false,
                "unlinkedCollapsed": true
              },
              "icon": "links-going-out",
              "title": "Outgoing links from design"
            }
          },
          {
            "id": "79643c5e8b69a676",
            "type": "leaf",
            "state": {
              "type": "tag",
              "state": {
                "sortOrder": "frequency",
                "useHierarchy": true,
                "showSearch": false,
                "searchQuery": ""
              },
              "icon": "lucide-tags",
              "title": "Tags"
            }
          },
          {
            "id": "17b2f58a145632cb",
            "type": "leaf",
            "state": {
              "type": "all-properties",
              "state": {
                "sortOrder": "frequency",
                "showSearch": false,
                "searchQuery": ""
              },
              "icon": "lucide-archive",
              "title": "All properties"
            }
          },
          {
            "id": "db234bcaee4df09e",
            "type": "leaf",
            "state": {
              "type": "outline",
              "state": {
                "file": "design.md",
                "followCursor": false,
                "showSearch": false,
                "searchQuery": ""
              },
              "icon": "lucide-list",
              "title": "Outline of design"
            }
          }
        ]
      }
    ],
    "direction": "horizontal",
    "width": 300,
    "collapsed": true
  },
  "left-ribbon": {
    "hiddenItems": {
      "switcher:Open quick switcher": false,
      "graph:Open graph view": false,
      "canvas:Create new canvas": false,
      "daily-notes:Open today's daily note": false,
      "templates:Insert template": false,
      "command-palette:Open command palette": false,
      "bases:Create new base": false
    }
  },
  "active": "efce14b5c734110f",
  "lastOpenFiles": [
    "services.md",
    "list of lines.md",
    "stations/crest park.md",
    "stations/broad park.md",
    "stations/woodland square.md",
    "stations/emerson hills.md",
    "stations/kent ridge.md",
    "stations/heather heights.md",
    "stations/dean hills.md",
    "stations/fawn park.md",
    "stations/empire district.md",
    "stations/crescent hills.md",
    "stations/meadow hills.md",
    "stations/summit valley.md",
    "stations/cherry hills.md",
    "stations/primrose park.md",
    "stations/orchard hills.md",
    "stations/linden park.md",
    "stations/cypress square.md",
    "stations/myrtle district.md",
    "stations/barlow heights.md",
    "stations/smith square.md",
    "stations/high park.md",
    "stations/fairview square.md",
    "stations/south coast.md",
    "stations/north coast.md",
    "assets/navigation/woodland square.svg",
    "assets/stations/woodland square.svg",
    "assets/navigation/victoria heights.svg",
    "assets/stations/victoria heights.svg",
    "assets/navigation/underhill grove.svg",
    "assets/stations/underhill grove.svg",
    "assets/navigation/thumb district.svg",
    "assets/stations/thumb district.svg",
    "assets/navigation/thornton park.svg",
    "assets/stations/thornton park.svg",
    "assets/navigation",
    "assets/stations",
    "assets/platforms",
    "assets/codes",
    "scripts/metro.db-journal",
    "metro.db-journal",
    "metro.db",
    "scripts/refresh",
    "scripts/__pycache__/misc.cpython-314.pyc",
    "scripts/__pycache__"
  ]
}